resistant_documents_client/__init__.py
resistant_documents_client/base.py
resistant_documents_client/client.py
resistant_documents_client/model.py
resistant_documents_client/tests/__init__.py
resistant_documents_client/tests/test_client.py
resistant_documents_client-2.4.3.dist-info/LICENSE
resistant_documents_client-2.4.3.dist-info/WHEEL
resistant_documents_client-2.4.3.dist-info/METADATA
resistant_documents_client-2.4.3.dist-info/RECORD
