Metadata-Version: 2.1
Name: resistant-documents-client
Version: 2.4.3
Summary: Resistant.ai document forjerry python client for convenient integration with REST API service.
Author: Resistant.ai
Author-email: sales@resistant.ai
Requires-Python: >=3.7,<4.0
Classifier: Programming Language :: Python :: 3
Classifier: Programming Language :: Python :: 3.7
Classifier: Programming Language :: Python :: 3.8
Classifier: Programming Language :: Python :: 3.9
Classifier: Programming Language :: Python :: 3.10
Classifier: Programming Language :: Python :: 3.11
Requires-Dist: requests (>=2.22.0,<3.0.0)
Requires-Dist: requests-oauthlib (>=1.3.0,<2.0.0)
